setup.cfg
setup.py
django_lite/__init__.py
django_lite/django_lite.py
django_lite/services.py
django_lite/templates.py
django_lite/utils.py
django_lite.egg-info/PKG-INFO
django_lite.egg-info/SOURCES.txt
django_lite.egg-info/dependency_links.txt
django_lite.egg-info/not-zip-safe
django_lite.egg-info/pbr.json
django_lite.egg-info/requires.txt
django_lite.egg-info/top_level.txt