Metadata-Version: 1.1
Name: django-lite
Version: 0.2.0
Summary: A light version of Django.
Home-page: https://github.com/fmarco/django-lite
Author: fmarco
Author-email: federighi.marco@gmail.com
License: MIT
Platform: OS Independent
Classifier: Environment :: Web Environment
Classifier: Intended Audience :: Developers
Classifier: License :: OSI Approved :: MIT License
Classifier: Operating System :: OS Independent
Classifier: Programming Language :: Python
Classifier: Topic :: Internet :: WWW/HTTP :: Dynamic Content
Classifier: Topic :: Software Development :: Libraries :: Python Modules
